{
    "types": [{
            "type": 1,
            "tittle": "资金账户"
        },
        {
            "type": 2,
            "tittle": "信用账户"
        },
        {
            "type": 3,
            "tittle": "充值账户"
        },
        {
            "type": 4,
            "tittle": "投资账户"
        }
    ],
    "list": [{
            "type": 1,
            "name": "现金",
            "icon": "cash"
        },
        {
            "type": 1,
            "name": "银行卡",
            "icon": "bankCard"
        },
        {
            "type": 1,
            "name": "微信",
            "icon": "wechat"
        },
        {
            "type": 1,
            "name": "支付宝",
            "icon": "alipay"
        },
        {
            "type": 1,
            "name": "公积金",
            "icon": "accumulationFund"
        },
        {
            "type": 1,
            "name": "社保",
            "icon": "socialFund"
        },
        {
            "type": 1,
            "name": "其他现金账户",
            "icon": "other"
        },
        {
            "type": 2,
            "name": "信用卡",
            "icon": "creditCard"
        },
        {
            "type": 2,
            "name": "蚂蚁花呗",
            "icon": "aliHuabei"
        },
        {
            "type": 2,
            "name": "京东白条",
            "icon": "jd"
        },
        {
            "type": 2,
            "name": "其他信用账户",
            "icon": "other"
        },
        {
            "type": 3,
            "name": "公交卡",
            "icon": "bus"
        },
        {
            "type": 3,
            "name": "饭卡",
            "icon": "meal"
        },
        {
            "type": 3,
            "name": "会员卡",
            "icon": "member"
        },
        {
            "type": 3,
            "name": "其他充值账户",
            "icon": "other"
        },
        {
            "type": 4,
            "name": "股票",
            "icon": "stocks"
        },
        {
            "type": 4,
            "name": "基金",
            "icon": "funds"
        },
        {
            "type": 4,
            "name": "其他投资账户",
            "icon": "other"
        }
    ]
}
